rastafari-0.2.3.dist-info/LICENSE
rastafari-0.2.3.dist-info/RECORD
rastafari-0.2.3.dist-info/METADATA
rastafari-0.2.3.dist-info/WHEEL
rastafari-0.2.3.dist-info/top_level.txt
rastafari/__init__.py
rastafari/py.typed
rastafari/core.pyi
rastafari/core.cpython-310-x86_64-linux-gnu.so
