Metadata-Version: 2.1
Name: rastafari
Version: 0.2.3
Summary: Rasterize vector features to grids
Home-page: https://gitlab.com/foclair/rastafari
Author: David Segersson, Eef van Dongen
Author-email: david.segersson@smhi.se
License: "see LICENSE file"
Project-URL: Bug Tracker, https://gitlab.com/foclair/rastafari/-/issues
Keywords: rasterize,DDA,resample
Classifier: License :: OSI Approved :: MIT License
Classifier: Programming Language :: Python :: 3
Requires-Python: >=3.9
Provides-Extra: test
License-File: LICENSE
